jefferson_street_api/__init__.py
jefferson_street_api/core.py
jefferson_street_api/queries.py
jefferson_street_api-0.1.0.dist-info/WHEEL
jefferson_street_api-0.1.0.dist-info/METADATA
jefferson_street_api-0.1.0.dist-info/RECORD
